{
    "name": "4x_GameAI_1.0",
    "author": "tal",
    "license": "WTFPL",
    "tags": [
        "image"
    ],
    "description": "Category: Game Screenshots\nPurpose: PS2 textures, cartoonish and realistic game textures.\nPretrained: 4x_GameAI_1.0\n\nThis model is intended to mainly handle PS2 compression and a mixture of Realistic and cartoonish textures, it's not meant to be used for very low resolution textures such as item icons. Dataset: I used textures from, \"(A Hat in Time, Kingdom Hearts 3 and World of Final Fantasy) for GameAI_2.0\" \"(Skyrim, The Witcher 3, Resident Evil 4, Final Fantasy XV and Tales of Vesperia ) for GameAI_1.0\" Dataset_size: 21.9k to 70k textures , up to 1024x1024 per texture",
    "date": "2022-02-27",
    "architecture": "ESRGAN",
    "size": [
        "64nf",
        "23nb"
    ],
    "scale": 4,
    "inputChannels": 3,
    "outputChannels": 3,
    "resources": [
        {
            "type": "pth",
            "size": 66961958,
            "sha256": "3b7b863ea6b083fb136ab00de7a492b8eeb07e7a1d1884f3ec395525aaedba54",
            "urls": [
                "https://drive.google.com/file/d/15KhApV05F8nEqTa5ZjLE821rhe1k8VOg/view?usp=sharing",
                "https://drive.google.com/file/d/1-s7iSK9ivJaoyvTXwDZvMjuyGG72bTQA/view?usp=sharing"
            ]
        }
    ]
}