{
    "name": "Lady0101",
    "author": "dinjerr",
    "license": null,
    "tags": [
        "image",
        "pixel-art"
    ],
    "description": "Category: Art/Pixel Art\nPurpose: Pixel Art/Paintings\n\nUpscale pixel art/paintings to digital painting style",
    "date": "2019-07-25",
    "architecture": "esrgan",
    "size": [
        "64nf",
        "23nb"
    ],
    "scale": 4,
    "inputChannels": 3,
    "outputChannels": 3,
    "resources": [
        {
            "platform": "pytorch",
            "type": "pth",
            "size": 66958607,
            "sha256": "408f539ec467427e60eb47793f59d1c589dd3cf1ae222f4001f376c0cb908638",
            "urls": [
                "https://1drv.ms/u/s!Aip-EMByJHY20xsc9EvnxVZ50Ja7?e=Loa5Gz"
            ]
        }
    ],
    "trainingIterations": 208000,
    "pretrainedModelG": "4x-WaifuGAN-v3"
}