{
    "name": "RealESRGAN_x4plus",
    "author": "xinntao",
    "license": null,
    "tags": [],
    "description": "Official pretrain model",
    "date": "2021-07-22",
    "architecture": "esrgan",
    "size": null,
    "scale": 4,
    "inputChannels": 3,
    "outputChannels": 3,
    "resources": [
        {
            "platform": "pytorch",
            "type": "pth",
            "size": 67040989,
            "sha256": "4fa0d38905f75ac06eb49a7951b426670021be3018265fd191d2125df9d682f1",
            "urls": [
                "https://github.com/xinntao/Real-ESRGAN/releases/download/v0.1.0/RealESRGAN_x4plus.pth"
            ]
        }
    ],
    "images": []
}